{
  "index.html": 1703239042341,
  "i18n/i18n_tr.properties": 1703227670000,
  "blocks/SalaryBlockController.controller.js": 1703227670000,
  "utils/ODataHelper.js": 1703227670000,
  "utils/locate-reuse-libs.js": 1703227670000,
  "utils/formatter.js": 1703227670000,
  "test/locate-reuse-libs.js": 1703239042350,
  "model/models.js": 1703227670000,
  "localService/mockserver.js": 1703227670000,
  "ext/lodash.js": 1703227670000,
  "ext/ApexCharts.js": 1703227670000,
  "controls/SmodApexChart.js": 1703227670000,
  "controls/ActionCard.js": 1703227670000,
  "controller/ProfileOverview.controller.js": 1703227670000,
  "controller/ErrorHandler.js": 1703227670000,
  "controller/BaseController.js": 1703227670000,
  "controller/Application.js": 1703227670000,
  "controller/App.controller.js": 1703227670000,
  "blocks/WorkExperienceBlockController.controller.js": 1703227670000,
  "blocks/WorkExperienceBlock.js": 1703227670000,
  "blocks/TrainingsBlockController.controller.js": 1703227670000,
  "blocks/TrainingsBlock.js": 1703227670000,
  "blocks/TimeRecordingBlockController.controller.js": 1703227670000,
  "blocks/TimeRecordingBlock.js": 1703227670000,
  "blocks/TimeBalanceBlockController.controller.js": 1703227670000,
  "blocks/TimeBalanceBlock.js": 1703227670000,
  "utils/reuseHandler.js": 1703227670000,
  "blocks/SalaryBlock.js": 1703227670000,
  "blocks/QualificationsBlockController.controller.js": 1703227670000,
  "blocks/QualificationsBlock.js": 1703227670000,
  "blocks/PersInfoPersonalDataBlockController.controller.js": 1703227670000,
  "blocks/PersInfoPersonalDataBlock.js": 1703227670000,
  "blocks/PersInfoInternalDataBlockController.controller.js": 1703227670000,
  "blocks/PersInfoInternalDataBlock.js": 1703227670000,
  "blocks/PersInfoFamilyMembersBlockController.controller.js": 1703227670000,
  "blocks/PersInfoFamilyMembersBlock.js": 1703227670000,
  "blocks/PersInfoCommunicationDataBlockController.controller.js": 1703227670000,
  "blocks/PersInfoCommunicationDataBlock.js": 1703227670000,
  "blocks/PersInfoBankBlockController.controller.js": 1703227670000,
  "blocks/PersInfoBankBlock.js": 1703227670000,
  "blocks/PersInfoAddressBlockController.controller.js": 1703227670000,
  "blocks/PersInfoAddressBlock.js": 1703227670000,
  "blocks/PerformanceBlockController.controller.js": 1703227670000,
  "blocks/PerformanceBlock.js": 1703227670000,
  "blocks/PaystubsBlockController.controller.js": 1703227670000,
  "blocks/PaystubsBlock.js": 1703227670000,
  "blocks/MultipleSkillsBlockController.controller.js": 1703227670000,
  "blocks/MultipleSkillsBlock.js": 1703227670000,
  "blocks/ForeignLanguageBlockController.controller.js": 1703227670000,
  "blocks/ForeignLanguageBlock.js": 1703227670000,
  "blocks/EducationBlockController.controller.js": 1703227670000,
  "blocks/EducationBlock.js": 1703227670000,
  "blocks/CourseBlockController.controller.js": 1703227670000,
  "blocks/CourseBlock.js": 1703227670000,
  "blocks/CertificateBlockController.controller.js": 1703227670000,
  "blocks/CertificateBlock.js": 1703227670000,
  "blocks/CareerProgressBlockController.controller.js": 1703227670000,
  "blocks/CareerProgressBlock.js": 1703227670000,
  "blocks/AbsenceBlockController.controller.js": 1703227670000,
  "blocks/AbsenceBlock.js": 1703227670000,
  "resources.json": 1703227670000,
  "manifest.json": 1703239042302,
  "Component.js": 1703227670000,
  "Component-preload.js": 1703241208387,
  "controls/ActionCard-dbg.js": 1703227670000,
  "controls/ActionCard.js.map": 1703241202345,
  "utils/ODataHelper-dbg.js": 1703227670000,
  "utils/ODataHelper.js.map": 1703241202178,
  "utils/locate-reuse-libs-dbg.js": 1703227670000,
  "utils/locate-reuse-libs.js.map": 1703241202346,
  "utils/formatter-dbg.js": 1703227670000,
  "utils/formatter.js.map": 1703241202427,
  "test/locate-reuse-libs-dbg.js": 1703239042350,
  "test/locate-reuse-libs.js.map": 1703241202353,
  "model/models-dbg.js": 1703227670000,
  "model/models.js.map": 1703241202377,
  "localService/mockserver-dbg.js": 1703227670000,
  "localService/mockserver.js.map": 1703241202408,
  "ext/lodash-dbg.js": 1703227670000,
  "ext/lodash.js.map": 1703241204342,
  "ext/ApexCharts-dbg.js": 1703227670000,
  "ext/ApexCharts.js.map": 1703241206649,
  "controls/SmodApexChart-dbg.js": 1703227670000,
  "controls/SmodApexChart.js.map": 1703241202555,
  "blocks/SalaryBlockController-dbg.controller.js": 1703227670000,
  "blocks/SalaryBlockController.controller.js.map": 1703241202614,
  "controller/ProfileOverview-dbg.controller.js": 1703227670000,
  "controller/ProfileOverview.controller.js.map": 1703241202817,
  "controller/ErrorHandler-dbg.js": 1703227670000,
  "controller/ErrorHandler.js.map": 1703241202754,
  "controller/BaseController-dbg.js": 1703227670000,
  "controller/BaseController.js.map": 1703241202814,
  "controller/Application-dbg.js": 1703227670000,
  "controller/Application.js.map": 1703241202927,
  "controller/App-dbg.controller.js": 1703227670000,
  "controller/App.controller.js.map": 1703241202828,
  "blocks/WorkExperienceBlockController-dbg.controller.js": 1703227670000,
  "blocks/WorkExperienceBlockController.controller.js.map": 1703241202917,
  "blocks/WorkExperienceBlock-dbg.js": 1703227670000,
  "blocks/WorkExperienceBlock.js.map": 1703241202917,
  "blocks/TrainingsBlockController-dbg.controller.js": 1703227670000,
  "blocks/TrainingsBlockController.controller.js.map": 1703241202957,
  "blocks/TrainingsBlock-dbg.js": 1703227670000,
  "blocks/TrainingsBlock.js.map": 1703241202935,
  "blocks/TimeRecordingBlockController-dbg.controller.js": 1703227670000,
  "blocks/TimeRecordingBlockController.controller.js.map": 1703241202968,
  "blocks/TimeRecordingBlock-dbg.js": 1703227670000,
  "blocks/TimeRecordingBlock.js.map": 1703241202973,
  "blocks/TimeBalanceBlockController-dbg.controller.js": 1703227670000,
  "blocks/TimeBalanceBlockController.controller.js.map": 1703241203035,
  "blocks/TimeBalanceBlock-dbg.js": 1703227670000,
  "blocks/TimeBalanceBlock.js.map": 1703241202984,
  "utils/reuseHandler-dbg.js": 1703227670000,
  "utils/reuseHandler.js.map": 1703241203036,
  "blocks/SalaryBlock-dbg.js": 1703227670000,
  "blocks/SalaryBlock.js.map": 1703241203060,
  "blocks/QualificationsBlockController-dbg.controller.js": 1703227670000,
  "blocks/QualificationsBlockController.controller.js.map": 1703241203092,
  "blocks/QualificationsBlock-dbg.js": 1703227670000,
  "blocks/QualificationsBlock.js.map": 1703241203092,
  "blocks/PersInfoPersonalDataBlockController-dbg.controller.js": 1703227670000,
  "blocks/PersInfoPersonalDataBlockController.controller.js.map": 1703241203110,
  "blocks/PersInfoPersonalDataBlock-dbg.js": 1703227670000,
  "blocks/PersInfoPersonalDataBlock.js.map": 1703241203109,
  "blocks/PersInfoInternalDataBlockController-dbg.controller.js": 1703227670000,
  "blocks/PersInfoInternalDataBlockController.controller.js.map": 1703241203126,
  "blocks/PersInfoInternalDataBlock-dbg.js": 1703227670000,
  "blocks/PersInfoInternalDataBlock.js.map": 1703241203118,
  "blocks/PersInfoFamilyMembersBlockController-dbg.controller.js": 1703227670000,
  "blocks/PersInfoFamilyMembersBlockController.controller.js.map": 1703241203128,
  "blocks/PersInfoFamilyMembersBlock-dbg.js": 1703227670000,
  "blocks/PersInfoFamilyMembersBlock.js.map": 1703241203131,
  "blocks/PersInfoCommunicationDataBlockController-dbg.controller.js": 1703227670000,
  "blocks/PersInfoCommunicationDataBlockController.controller.js.map": 1703241203147,
  "blocks/PersInfoCommunicationDataBlock-dbg.js": 1703227670000,
  "blocks/PersInfoCommunicationDataBlock.js.map": 1703241203141,
  "blocks/PersInfoBankBlockController-dbg.controller.js": 1703227670000,
  "blocks/PersInfoBankBlockController.controller.js.map": 1703241203172,
  "blocks/PersInfoBankBlock-dbg.js": 1703227670000,
  "blocks/PersInfoBankBlock.js.map": 1703241203161,
  "blocks/PersInfoAddressBlockController-dbg.controller.js": 1703227670000,
  "blocks/PersInfoAddressBlockController.controller.js.map": 1703241203227,
  "blocks/PersInfoAddressBlock-dbg.js": 1703227670000,
  "blocks/PersInfoAddressBlock.js.map": 1703241203191,
  "blocks/PerformanceBlockController-dbg.controller.js": 1703227670000,
  "blocks/PerformanceBlockController.controller.js.map": 1703241203333,
  "blocks/PerformanceBlock-dbg.js": 1703227670000,
  "blocks/PerformanceBlock.js.map": 1703241203231,
  "blocks/PaystubsBlockController-dbg.controller.js": 1703227670000,
  "blocks/PaystubsBlockController.controller.js.map": 1703241203282,
  "blocks/PaystubsBlock-dbg.js": 1703227670000,
  "blocks/PaystubsBlock.js.map": 1703241203288,
  "blocks/MultipleSkillsBlockController-dbg.controller.js": 1703227670000,
  "blocks/MultipleSkillsBlockController.controller.js.map": 1703241203329,
  "blocks/MultipleSkillsBlock-dbg.js": 1703227670000,
  "blocks/MultipleSkillsBlock.js.map": 1703241203497,
  "blocks/ForeignLanguageBlockController-dbg.controller.js": 1703227670000,
  "blocks/ForeignLanguageBlockController.controller.js.map": 1703241203392,
  "blocks/ForeignLanguageBlock-dbg.js": 1703227670000,
  "blocks/ForeignLanguageBlock.js.map": 1703241203354,
  "blocks/EducationBlockController-dbg.controller.js": 1703227670000,
  "blocks/EducationBlockController.controller.js.map": 1703241203360,
  "blocks/EducationBlock-dbg.js": 1703227670000,
  "blocks/EducationBlock.js.map": 1703241203372,
  "blocks/CourseBlockController-dbg.controller.js": 1703227670000,
  "blocks/CourseBlockController.controller.js.map": 1703241203418,
  "blocks/CourseBlock-dbg.js": 1703227670000,
  "blocks/CourseBlock.js.map": 1703241203404,
  "blocks/CertificateBlockController-dbg.controller.js": 1703227670000,
  "blocks/CertificateBlockController.controller.js.map": 1703241203447,
  "blocks/CertificateBlock-dbg.js": 1703227670000,
  "blocks/CertificateBlock.js.map": 1703241203429,
  "blocks/CareerProgressBlockController-dbg.controller.js": 1703227670000,
  "blocks/CareerProgressBlockController.controller.js.map": 1703241203458,
  "blocks/CareerProgressBlock-dbg.js": 1703227670000,
  "blocks/CareerProgressBlock.js.map": 1703241203453,
  "blocks/AbsenceBlockController-dbg.controller.js": 1703227670000,
  "blocks/AbsenceBlockController.controller.js.map": 1703241203488,
  "blocks/AbsenceBlock-dbg.js": 1703227670000,
  "blocks/AbsenceBlock.js.map": 1703241203464,
  "Component-dbg.js": 1703227670000,
  "Component.js.map": 1703241203490,
  "Component-preload-dbg.js": 1703227670000,
  "Component-preload.js.map": 1703241208394,
  "view/fragment/OfficeInfoQuickview.fragment.xml": 1703227670000,
  "view/fragment/ObjectPageSections.fragment.xml": 1703227670000,
  "view/fragment/ManagerQuickview.fragment.xml": 1703227670000,
  "view/fragment/EmployeeSearch.fragment.xml": 1703227670000,
  "view/fragment/DirectReportsList.fragment.xml": 1703227670000,
  "view/fragment/ColleaguesList.fragment.xml": 1703227670000,
  "blocks/fragments/WorkExperienceChangeRequest.fragment.xml": 1703227670000,
  "blocks/fragments/PersInfoAddressChangeRequest.fragment.xml": 1703227670000,
  "blocks/fragments/ForeignLanguageChangeRequest.fragment.xml": 1703227670000,
  "blocks/fragments/CourseChangeRequest.fragment.xml": 1703227670000,
  "blocks/fragments/CertificateChangeRequest.fragment.xml": 1703227670000,
  "css/assets/smodfont.woff": 1703227670000,
  "css/assets/smodfont.ttf": 1703227670000,
  "css/assets/smodfont.svg": 1703227670000,
  "css/assets/smodfont.eot": 1703227670000,
  "view/ProfileOverview.view.xml": 1703227670000,
  "view/App.view.xml": 1703227670000,
  "test/flpSandboxMockServer.html": 1703239042465,
  "test/flpSandbox.html": 1703239042403,
  "localService/metadata.xml": 1703227670000,
  "ext/customStyles.css": 1703227670000,
  "ext/ApexCharts.css": 1703227670000,
  "css/custom.css": 1703227670000,
  "controls/ActionCard.css": 1703227670000,
  "blocks/WorkExperienceBlock.view.xml": 1703227670000,
  "blocks/TrainingsBlockPhone.view.xml": 1703227670000,
  "blocks/TrainingsBlock.view.xml": 1703227670000,
  "blocks/TimeRecordingBlock.view.xml": 1703227670000,
  "blocks/TimeBalanceBlock.view.xml": 1703227670000,
  "blocks/SalaryBlock.view.xml": 1703227670000,
  "blocks/QualificationsBlockPhone.view.xml": 1703227670000,
  "blocks/QualificationsBlock.view.xml": 1703227670000,
  "blocks/PersInfoPersonalDataBlock.view.xml": 1703227670000,
  "blocks/PersInfoInternalDataBlock.view.xml": 1703227670000,
  "blocks/PersInfoFamilyMembersBlockExpanded.view.xml": 1703227670000,
  "blocks/PersInfoFamilyMembersBlockCollapsed.view.xml": 1703227670000,
  "blocks/PersInfoCommunicationDataBlock.view.xml": 1703227670000,
  "blocks/PersInfoBankBlockExpanded.view.xml": 1703227670000,
  "blocks/PersInfoBankBlockCollapsed.view.xml": 1703227670000,
  "blocks/PersInfoAddressBlockExpanded.view.xml": 1703227670000,
  "blocks/PersInfoAddressBlockCollapsed.view.xml": 1703227670000,
  "blocks/PerformanceBlockV2.view.xml": 1703227670000,
  "blocks/PerformanceBlock.view.xml": 1703227670000,
  "blocks/PaystubsBlockPhone.view.xml": 1703227670000,
  "blocks/PaystubsBlockExpandedList.view.xml": 1703227670000,
  "blocks/PaystubsBlockExpanded.view.xml": 1703227670000,
  "blocks/PaystubsBlockCollapsed.view.xml": 1703227670000,
  "blocks/MultipleSkillsBlock.view.xml": 1703227670000,
  "blocks/ForeignLanguageBlock.view.xml": 1703227670000,
  "blocks/EducationBlock.view.xml": 1703227670000,
  "blocks/CourseBlock.view.xml": 1703227670000,
  "blocks/CertificateBlock.view.xml": 1703227670000,
  "blocks/CareerProgressBlock.view.xml": 1703227670000,
  "blocks/AbsenceBlock.view.xml": 1703227670000,
  "i18n/i18n.properties": 1703227670000
}